{
  "category": "CUSTOM",
  "displayName": "quotas_utilization",
  "mosaicLayout": {
    "columns": 12,
    "tiles": [
      {
        "height": 4,
        "widget": {
          "title": "internal_forwarding_rules_l4_utilization",
          "xyChart": {
            "chartOptions": {
              "mode": "COLOR"
            },
            "dataSets": [
              {
                "minAlignmentPeriod": "3600s",
                "plotType": "LINE",
                "targetAxis": "Y1",
                "timeSeriesQuery": {
                  "apiSource": "DEFAULT_CLOUD",
                  "timeSeriesFilter": {
                    "aggregation": {
                      "alignmentPeriod": "3600s",
                      "perSeriesAligner": "ALIGN_NEXT_OLDER"
                    },
                    "filter": "metric.type=\"custom.googleapis.com/internal_forwarding_rules_l4_utilization\" resource.type=\"global\"",
                    "secondaryAggregation": {
                      "alignmentPeriod": "1800s",
                      "perSeriesAligner": "ALIGN_MEAN"
                    }
                  }
                }
              }
            ],
            "timeshiftDuration": "0s",
            "yAxis": {
              "label": "y1Axis",
              "scale": "LINEAR"
            }
          }
        },
        "width": 6,
        "xPos": 0,
        "yPos": 0
      },
      {
        "height": 4,
        "widget": {
          "title": "internal_forwarding_rules_l7_utilization",
          "xyChart": {
            "chartOptions": {
              "mode": "COLOR"
            },
            "dataSets": [
              {
                "minAlignmentPeriod": "3600s",
                "plotType": "LINE",
                "targetAxis": "Y1",
                "timeSeriesQuery": {
                  "apiSource": "DEFAULT_CLOUD",
                  "timeSeriesFilter": {
                    "aggregation": {
                      "alignmentPeriod": "3600s",
                      "perSeriesAligner": "ALIGN_NEXT_OLDER"
                    },
                    "filter": "metric.type=\"custom.googleapis.com/internal_forwarding_rules_l7_utilization\" resource.type=\"global\"",
                    "secondaryAggregation": {
                      "alignmentPeriod": "60s",
                      "perSeriesAligner": "ALIGN_MEAN"
                    }
                  }
                }
              }
            ],
            "timeshiftDuration": "0s",
            "yAxis": {
              "label": "y1Axis",
              "scale": "LINEAR"
            }
          }
        },
        "width": 6,
        "xPos": 0,
        "yPos": 12
      },
      {
        "height": 4,
        "widget": {
          "title": "number_of_instances_utilization",
          "xyChart": {
            "chartOptions": {
              "mode": "COLOR"
            },
            "dataSets": [
              {
                "minAlignmentPeriod": "3600s",
                "plotType": "LINE",
                "targetAxis": "Y1",
                "timeSeriesQuery": {
                  "apiSource": "DEFAULT_CLOUD",
                  "timeSeriesFilter": {
                    "aggregation": {
                      "alignmentPeriod": "3600s",
                      "perSeriesAligner": "ALIGN_NEXT_OLDER"
                    },
                    "filter": "metric.type=\"custom.googleapis.com/number_of_instances_utilization\" resource.type=\"global\"",
                    "secondaryAggregation": {
                      "alignmentPeriod": "60s",
                      "perSeriesAligner": "ALIGN_MEAN"
                    }
                  }
                }
              }
            ],
            "timeshiftDuration": "0s",
            "yAxis": {
              "label": "y1Axis",
              "scale": "LINEAR"
            }
          }
        },
        "width": 6,
        "xPos": 0,
        "yPos": 8
      },
      {
        "height": 4,
        "widget": {
          "title": "number_of_vpc_peerings_utilization",
          "xyChart": {
            "chartOptions": {
              "mode": "COLOR"
            },
            "dataSets": [
              {
                "minAlignmentPeriod": "3600s",
                "plotType": "LINE",
                "targetAxis": "Y1",
                "timeSeriesQuery": {
                  "apiSource": "DEFAULT_CLOUD",
                  "timeSeriesFilter": {
                    "aggregation": {
                      "alignmentPeriod": "3600s",
                      "perSeriesAligner": "ALIGN_NEXT_OLDER"
                    },
                    "filter": "metric.type=\"custom.googleapis.com/number_of_vpc_peerings_utilization\" resource.type=\"global\"",
                    "secondaryAggregation": {
                      "alignmentPeriod": "60s",
                      "perSeriesAligner": "ALIGN_MEAN"
                    }
                  }
                }
              }
            ],
            "timeshiftDuration": "0s",
            "yAxis": {
              "label": "y1Axis",
              "scale": "LINEAR"
            }
          }
        },
        "width": 6,
        "xPos": 6,
        "yPos": 4
      },
      {
        "height": 4,
        "widget": {
          "title": "number_of_active_vpc_peerings_utilization",
          "xyChart": {
            "chartOptions": {
              "mode": "COLOR"
            },
            "dataSets": [
              {
                "minAlignmentPeriod": "3600s",
                "plotType": "LINE",
                "targetAxis": "Y1",
                "timeSeriesQuery": {
                  "apiSource": "DEFAULT_CLOUD",
                  "timeSeriesFilter": {
                    "aggregation": {
                      "alignmentPeriod": "3600s",
                      "perSeriesAligner": "ALIGN_NEXT_OLDER"
                    },
                    "filter": "metric.type=\"custom.googleapis.com/number_of_active_vpc_peerings_utilization\" resource.type=\"global\"",
                    "secondaryAggregation": {
                      "alignmentPeriod": "60s",
                      "perSeriesAligner": "ALIGN_INTERPOLATE"
                    }
                  }
                }
              }
            ],
            "timeshiftDuration": "0s",
            "yAxis": {
              "label": "y1Axis",
              "scale": "LINEAR"
            }
          }
        },
        "width": 6,
        "xPos": 0,
        "yPos": 4
      },
      {
        "height": 4,
        "widget": {
          "title": "subnet_IP_ranges_ppg_utilization",
          "xyChart": {
            "chartOptions": {
              "mode": "COLOR"
            },
            "dataSets": [
              {
                "minAlignmentPeriod": "3600s",
                "plotType": "LINE",
                "targetAxis": "Y1",
                "timeSeriesQuery": {
                  "apiSource": "DEFAULT_CLOUD",
                  "timeSeriesFilter": {
                    "aggregation": {
                      "alignmentPeriod": "3600s",
                      "perSeriesAligner": "ALIGN_NEXT_OLDER"
                    },
                    "filter": "metric.type=\"custom.googleapis.com/number_of_subnet_IP_ranges_ppg_utilization\" resource.type=\"global\"",
                    "secondaryAggregation": {
                      "alignmentPeriod": "3600s",
                      "perSeriesAligner": "ALIGN_MEAN"
                    }
                  }
                }
              }
            ],
            "timeshiftDuration": "0s",
            "yAxis": {
              "label": "y1Axis",
              "scale": "LINEAR"
            }
          }
        },
        "width": 6,
        "xPos": 0,
        "yPos": 16
      },
      {
        "height": 4,
        "widget": {
          "title": "internal_forwarding_rules_l4_ppg_utilization",
          "xyChart": {
            "chartOptions": {
              "mode": "COLOR"
            },
            "dataSets": [
              {
                "minAlignmentPeriod": "3600s",
                "plotType": "LINE",
                "targetAxis": "Y1",
                "timeSeriesQuery": {
                  "apiSource": "DEFAULT_CLOUD",
                  "timeSeriesFilter": {
                    "aggregation": {
                      "alignmentPeriod": "3600s",
                      "perSeriesAligner": "ALIGN_NEXT_OLDER"
                    },
                    "filter": "metric.type=\"custom.googleapis.com/internal_forwarding_rules_l4_ppg_utilization\" resource.type=\"global\"",
                    "secondaryAggregation": {
                      "alignmentPeriod": "3600s",
                      "perSeriesAligner": "ALIGN_MEAN"
                    }
                  }
                }
              }
            ],
            "timeshiftDuration": "0s",
            "yAxis": {
              "label": "y1Axis",
              "scale": "LINEAR"
            }
          }
        },
        "width": 6,
        "xPos": 6,
        "yPos": 0
      },
      {
        "height": 4,
        "widget": {
          "title": "internal_forwarding_rules_l7_ppg_utilization",
          "xyChart": {
            "chartOptions": {
              "mode": "COLOR"
            },
            "dataSets": [
              {
                "minAlignmentPeriod": "3600s",
                "plotType": "LINE",
                "targetAxis": "Y1",
                "timeSeriesQuery": {
                  "apiSource": "DEFAULT_CLOUD",
                  "timeSeriesFilter": {
                    "aggregation": {
                      "alignmentPeriod": "3600s",
                      "perSeriesAligner": "ALIGN_NEXT_OLDER"
                    },
                    "filter": "metric.type=\"custom.googleapis.com/internal_forwarding_rules_l7_ppg_utilization\" resource.type=\"global\"",
                    "secondaryAggregation": {
                      "alignmentPeriod": "60s",
                      "perSeriesAligner": "ALIGN_MEAN"
                    }
                  }
                }
              }
            ],
            "timeshiftDuration": "0s",
            "yAxis": {
              "label": "y1Axis",
              "scale": "LINEAR"
            }
          }
        },
        "width": 6,
        "xPos": 6,
        "yPos": 12
      },
      {
        "height": 4,
        "widget": {
          "title": "number_of_instances_ppg_utilization",
          "xyChart": {
            "chartOptions": {
              "mode": "COLOR"
            },
            "dataSets": [
              {
                "minAlignmentPeriod": "3600s",
                "plotType": "LINE",
                "targetAxis": "Y1",
                "timeSeriesQuery": {
                  "apiSource": "DEFAULT_CLOUD",
                  "timeSeriesFilter": {
                    "aggregation": {
                      "alignmentPeriod": "3600s",
                      "perSeriesAligner": "ALIGN_NEXT_OLDER"
                    },
                    "filter": "metric.type=\"custom.googleapis.com/number_of_instances_ppg_utilization\" resource.type=\"global\""
                  }
                }
              }
            ],
            "timeshiftDuration": "0s",
            "yAxis": {
              "label": "y1Axis",
              "scale": "LINEAR"
            }
          }
        },
        "width": 6,
        "xPos": 6,
        "yPos": 8
      },
      {
        "height": 4,
        "widget": {
          "title": "dynamic_routes_per_network_utilization",
          "xyChart": {
            "chartOptions": {
              "mode": "COLOR"
            },
            "dataSets": [
              {
                "minAlignmentPeriod": "60s",
                "plotType": "LINE",
                "targetAxis": "Y1",
                "timeSeriesQuery": {
                  "apiSource": "DEFAULT_CLOUD",
                  "timeSeriesFilter": {
                    "aggregation": {
                      "alignmentPeriod": "60s",
                      "perSeriesAligner": "ALIGN_MEAN"
                    },
                    "filter": "metric.type=\"custom.googleapis.com/dynamic_routes_per_network_utilization\" resource.type=\"global\""
                  }
                }
              }
            ],
            "timeshiftDuration": "0s",
            "yAxis": {
              "label": "y1Axis",
              "scale": "LINEAR"
            }
          }
        },
        "width": 6,
        "xPos": 0,
        "yPos": 20
      },
      {
        "height": 4,
        "widget": {
          "title": "firewalls_per_project_vpc_usage",
          "xyChart": {
            "chartOptions": {
              "mode": "COLOR"
            },
            "dataSets": [
              {
                "minAlignmentPeriod": "60s",
                "plotType": "LINE",
                "targetAxis": "Y1",
                "timeSeriesQuery": {
                  "apiSource": "DEFAULT_CLOUD",
                  "timeSeriesFilter": {
                    "aggregation": {
                      "alignmentPeriod": "60s",
                      "crossSeriesReducer": "REDUCE_SUM",
                      "groupByFields": [
                        "metric.label.\"project\""
                      ],
                      "perSeriesAligner": "ALIGN_MEAN"
                    },
                    "filter": "metric.type=\"custom.googleapis.com/firewalls_per_project_vpc_usage\" resource.type=\"global\""
                  }
                }
              }
            ],
            "timeshiftDuration": "0s",
            "yAxis": {
              "label": "y1Axis",
              "scale": "LINEAR"
            }
          }
        },
        "width": 6,
        "xPos": 0,
        "yPos": 32
      },
      {
        "height": 4,
        "widget": {
          "title": "firewalls_per_project_utilization",
          "xyChart": {
            "chartOptions": {
              "mode": "COLOR"
            },
            "dataSets": [
              {
                "minAlignmentPeriod": "60s",
                "plotType": "LINE",
                "targetAxis": "Y1",
                "timeSeriesQuery": {
                  "apiSource": "DEFAULT_CLOUD",
                  "timeSeriesFilter": {
                    "aggregation": {
                      "alignmentPeriod": "60s",
                      "crossSeriesReducer": "REDUCE_MAX",
                      "groupByFields": [
                        "metric.label.\"project\""
                      ],
                      "perSeriesAligner": "ALIGN_MAX"
                    },
                    "filter": "metric.type=\"custom.googleapis.com/firewalls_per_project_utilization\" resource.type=\"global\""
                  }
                }
              }
            ],
            "timeshiftDuration": "0s",
            "yAxis": {
              "label": "y1Axis",
              "scale": "LINEAR"
            }
          }
        },
        "width": 6,
        "xPos": 6,
        "yPos": 32
      },
      {
        "height": 4,
        "widget": {
          "title": "tuples_per_firewall_policy_utilization",
          "xyChart": {
            "chartOptions": {
              "mode": "COLOR"
            },
            "dataSets": [
              {
                "minAlignmentPeriod": "60s",
                "plotType": "LINE",
                "targetAxis": "Y1",
                "timeSeriesQuery": {
                  "apiSource": "DEFAULT_CLOUD",
                  "timeSeriesFilter": {
                    "aggregation": {
                      "alignmentPeriod": "60s",
                      "perSeriesAligner": "ALIGN_MEAN"
                    },
                    "filter": "metric.type=\"custom.googleapis.com/firewall_policy_tuples_per_policy_utilization\" resource.type=\"global\""
                  }
                }
              }
            ],
            "timeshiftDuration": "0s",
            "yAxis": {
              "label": "y1Axis",
              "scale": "LINEAR"
            }
          }
        },
        "width": 6,
        "xPos": 6,
        "yPos": 28
      },
      {
        "height": 4,
        "widget": {
          "title": "ip_addresses_per_subnet_utilization",
          "xyChart": {
            "chartOptions": {
              "mode": "COLOR"
            },
            "dataSets": [
              {
                "minAlignmentPeriod": "60s",
                "plotType": "LINE",
                "targetAxis": "Y1",
                "timeSeriesQuery": {
                  "apiSource": "DEFAULT_CLOUD",
                  "timeSeriesFilter": {
                    "aggregation": {
                      "alignmentPeriod": "60s",
                      "perSeriesAligner": "ALIGN_MEAN"
                    },
                    "filter": "metric.type=\"custom.googleapis.com/ip_addresses_per_subnet_utilization\" resource.type=\"global\""
                  }
                }
              }
            ],
            "timeshiftDuration": "0s",
            "yAxis": {
              "label": "y1Axis",
              "scale": "LINEAR"
            }
          }
        },
        "width": 6,
        "xPos": 6,
        "yPos": 16
      },
      {
        "height": 4,
        "widget": {
          "title": "dynamic_routes_ppg_utilization",
          "xyChart": {
            "chartOptions": {
              "mode": "COLOR"
            },
            "dataSets": [
              {
                "minAlignmentPeriod": "60s",
                "plotType": "LINE",
                "targetAxis": "Y1",
                "timeSeriesQuery": {
                  "apiSource": "DEFAULT_CLOUD",
                  "timeSeriesFilter": {
                    "aggregation": {
                      "alignmentPeriod": "60s",
                      "perSeriesAligner": "ALIGN_MEAN"
                    },
                    "filter": "metric.type=\"custom.googleapis.com/dynamic_routes_per_peering_group_utilization\" resource.type=\"global\""
                  }
                }
              }
            ],
            "timeshiftDuration": "0s",
            "yAxis": {
              "label": "y1Axis",
              "scale": "LINEAR"
            }
          }
        },
        "width": 6,
        "xPos": 6,
        "yPos": 20
      },
      {
        "height": 4,
        "widget": {
          "title": "static_routes_per_project_vpc_usage",
          "xyChart": {
            "chartOptions": {
              "mode": "COLOR"
            },
            "dataSets": [
              {
                "minAlignmentPeriod": "60s",
                "plotType": "LINE",
                "targetAxis": "Y1",
                "timeSeriesQuery": {
                  "apiSource": "DEFAULT_CLOUD",
                  "timeSeriesFilter": {
                    "aggregation": {
                      "alignmentPeriod": "60s",
                      "crossSeriesReducer": "REDUCE_SUM",
                      "groupByFields": [
                        "metric.label.\"project\""
                      ],
                      "perSeriesAligner": "ALIGN_MEAN"
                    },
                    "filter": "metric.type=\"custom.googleapis.com/static_routes_per_project_vpc_usage\" resource.type=\"global\"",
                    "secondaryAggregation": {
                      "alignmentPeriod": "60s",
                      "perSeriesAligner": "ALIGN_NONE"
                    }
                  }
                }
              }
            ],
            "thresholds": [],
            "timeshiftDuration": "0s",
            "yAxis": {
              "label": "y1Axis",
              "scale": "LINEAR"
            }
          }
        },
        "width": 6,
        "xPos": 0,
        "yPos": 24
      },
      {
        "height": 4,
        "widget": {
          "title": "static_routes_per_ppg_utilization",
          "xyChart": {
            "chartOptions": {
              "mode": "COLOR"
            },
            "dataSets": [
              {
                "minAlignmentPeriod": "60s",
                "plotType": "LINE",
                "targetAxis": "Y1",
                "timeSeriesQuery": {
                  "apiSource": "DEFAULT_CLOUD",
                  "timeSeriesFilter": {
                    "aggregation": {
                      "alignmentPeriod": "60s",
                      "perSeriesAligner": "ALIGN_MEAN"
                    },
                    "filter": "metric.type=\"custom.googleapis.com/static_routes_per_peering_group_utilization\" resource.type=\"global\""
                  }
                }
              }
            ],
            "thresholds": [],
            "timeshiftDuration": "0s",
            "yAxis": {
              "label": "y1Axis",
              "scale": "LINEAR"
            }
          }
        },
        "width": 6,
        "xPos": 0,
        "yPos": 28
      },
      {
        "height": 4,
        "widget": {
          "title": "static_routes_per_project_utilization",
          "xyChart": {
            "chartOptions": {
              "mode": "COLOR"
            },
            "dataSets": [
              {
                "minAlignmentPeriod": "60s",
                "plotType": "LINE",
                "targetAxis": "Y1",
                "timeSeriesQuery": {
                  "apiSource": "DEFAULT_CLOUD",
                  "timeSeriesFilter": {
                    "aggregation": {
                      "alignmentPeriod": "60s",
                      "perSeriesAligner": "ALIGN_MEAN"
                    },
                    "filter": "metric.type=\"custom.googleapis.com/static_routes_per_project_utilization\" resource.type=\"global\""
                  }
                }
              }
            ],
            "timeshiftDuration": "0s",
            "yAxis": {
              "label": "y1Axis",
              "scale": "LINEAR"
            }
          }
        },
        "width": 6,
        "xPos": 6,
        "yPos": 24
      }
    ]
  }
}